textractor/__init__.py
textractor/utils.py
textractor/builtin_plugins/doc.py
textractor/builtin_plugins/odf.py
textractor/builtin_plugins/ooxml.py
textractor/builtin_plugins/pdf.py
textractor/builtin_plugins/text.py
textractor/fillwords/de.txt
textractor/fillwords/en.txt
TExtractor-0.1.2.dist-info/LICENSE
TExtractor-0.1.2.dist-info/METADATA
TExtractor-0.1.2.dist-info/WHEEL
TExtractor-0.1.2.dist-info/top_level.txt
TExtractor-0.1.2.dist-info/RECORD
